KeyWeighted/__init__.py
KeyWeighted/bisect.py
KeyWeighted/heapq.py
KeyWeighted-0.0.2.dist-info/METADATA
KeyWeighted-0.0.2.dist-info/WHEEL
KeyWeighted-0.0.2.dist-info/top_level.txt
KeyWeighted-0.0.2.dist-info/RECORD
