Metadata-Version: 2.1
Name: KeyWeighted
Version: 0.0.2
Summary: add option arg key to some lib
Home-page: https://github.com/HellOwhatAs/KeyWeighted
Author: HellOwhatAs
Author-email: xjq701229@outlook.com
License: MIT License
Platform: UNKNOWN
